MANIFEST.in
README.rst
requirements.txt
setup.py
pydic/__init__.py
pydic.egg-info/PKG-INFO
pydic.egg-info/SOURCES.txt
pydic.egg-info/dependency_links.txt
pydic.egg-info/not-zip-safe
pydic.egg-info/requires.txt
pydic.egg-info/top_level.txt