Metadata-Version: 1.0
Name: pydic
Version: 1.0.0
Summary: Manage your services via a robust and flexible Dependency Injection Container
Home-page: https://github.com/felixcarmona/pydic
Author: Felix Carmona
Author-email: mail@felixcarmona.com
License: UNKNOWN
Platform: UNKNOWN
